unpacking/__init__.py
unpacking/unpacking.py
unpacking-2024.0.7.dist-info/METADATA
unpacking-2024.0.7.dist-info/WHEEL
unpacking-2024.0.7.dist-info/licenses/LICENSE
unpacking-2024.0.7.dist-info/RECORD
