Metadata-Version: 2.3
Name: unpacking
Version: 2024.0.7
Summary: Unpacking or destructuring arguments in Python
Project-URL: Homepage, https://github.com/cctien/unpacking
Project-URL: Repository, https://github.com/cctien/unpacking
Project-URL: Issues, https://github.com/cctien/unpacking/issues
Author-email: Chih-chan Tien <chihchan.tien@gmail.com>
License:                                  Apache License
License-File: LICENSE
Keywords: destruct,destructing,destructure,destructuring,unpack,unpacked,unpacking
Classifier: Development Status :: 5 - Production/Stable
Classifier: License :: OSI Approved :: Apache Software License
Classifier: Operating System :: OS Independent
Classifier: Programming Language :: Python :: 3
Requires-Python: >=3.8
Requires-Dist: plum-dispatch>=2.5
Requires-Dist: toolz>=0.12
